pgox/char.cpython-38.so
pgox/char/__init__.py
pgox/char/char.py
pgox_char-0.0.2.dist-info/LICENSE
pgox_char-0.0.2.dist-info/METADATA
pgox_char-0.0.2.dist-info/WHEEL
pgox_char-0.0.2.dist-info/top_level.txt
pgox_char-0.0.2.dist-info/RECORD
