Metadata-Version: 2.1
Name: pgox-char
Version: 0.0.2
Summary: PGOX library that return a combination of ascii characters
Home-page: https://phoxett.github.io/pgox-char/
Author: Phoxett
Author-email: phoxett@gmail.com
Maintainer: Phoxett
Maintainer-email: phoxett@gmail.com
License: MIT
Platform: UNKNOWN
